.editorconfig
.gitignore
.travis.yml
AUTHORS.rst
CONTRIBUTING.rst
HISTORY.rst
LICENSE
MANIFEST.in
Makefile
README.md
pylint.ini
requirements_dev.txt
setup.cfg
setup.py
tox.ini
docs/Makefile
docs/authors.rst
docs/conf.py
docs/contributing.rst
docs/history.rst
docs/index.rst
docs/installation.rst
docs/make.bat
docs/readme.rst
docs/usage.rst
pyww3/__init__.py
pyww3/bounc.py
pyww3/cli.py
pyww3/grid.py
pyww3/namelists.py
pyww3/ounf.py
pyww3/ounp.py
pyww3/prnc.py
pyww3/shel.py
pyww3/utils.py
pyww3/ww3.py
pyww3.egg-info/PKG-INFO
pyww3.egg-info/SOURCES.txt
pyww3.egg-info/dependency_links.txt
pyww3.egg-info/entry_points.txt
pyww3.egg-info/not-zip-safe
pyww3.egg-info/requires.txt
pyww3.egg-info/top_level.txt