Metadata-Version: 2.1
Name: pyww3
Version: 0.1.4
Summary: Python wrapper for NOAA's WaveWatchIII Model
Home-page: https://github.com/caiostringari/pyww3
Author: Caio Stringari
Author-email: caio.stringari@gmail.com
License: GNU General Public License v3.0
Keywords: pyww3
Platform: UNKNOWN
Classifier: Development Status :: 2 - Pre-Alpha
Classifier: Intended Audience :: Developers
Classifier: License :: OSI Approved :: MIT License
Classifier: Natural Language :: English
Classifier: Programming Language :: Python :: 3
Classifier: Programming Language :: Python :: 3.7
Classifier: Programming Language :: Python :: 3.8
Requires-Python: >=3.7
License-File: LICENSE
License-File: AUTHORS.rst
